requirements.txt
grapp/__init__.py
grapp/version.py
grapp/assoc/__init__.py
grapp/cli/__init__.py
grapp/cli/assoc_cli.py
grapp/cli/export_cli.py
grapp/cli/filter_cli.py
grapp/cli/main.py
grapp/cli/pca_cli.py
grapp/cli/util.py
grapp/linalg/__init__.py
grapp/linalg/ops_scipy.py
grapp/linalg/proPCA.py
grapp/nn/__init__.py
grapp/util/__init__.py
grapp/util/filter.py
grapp/util/igd.py
grapp/util/simple.py
grapp-0.1.dist-info/LICENSE
grapp-0.1.dist-info/METADATA
grapp-0.1.dist-info/WHEEL
grapp-0.1.dist-info/entry_points.txt
grapp-0.1.dist-info/top_level.txt
grapp-0.1.dist-info/RECORD
