Metadata-Version: 2.1
Name: grapp
Version: 0.1
Summary: Statistical and population genetics methods on GRG
Home-page: https://aprilweilab.github.io/
Author: Drew DeHaas
Author-email: 
License: UNKNOWN
Platform: UNKNOWN
Classifier: Programming Language :: Python :: 3
Classifier: Programming Language :: Python :: 3.9
Classifier: Programming Language :: Python :: 3.10
Classifier: Programming Language :: Python :: 3.11
Classifier: Programming Language :: Python :: 3.12
Classifier: Programming Language :: Python :: 3.13
License-File: LICENSE
Requires-Dist: numpy
Requires-Dist: pandas
Requires-Dist: pygrgl>=2.2
Requires-Dist: pyigd>=1.3
Requires-Dist: scipy
